asserty/__init__.py
asserty/asserts.py
asserty/expected_error.py
asserty-3.0.0.dist-info/LICENSE
asserty-3.0.0.dist-info/METADATA
asserty-3.0.0.dist-info/WHEEL
asserty-3.0.0.dist-info/top_level.txt
asserty-3.0.0.dist-info/RECORD
