Metadata-Version: 2.1
Name: asserty
Version: 3.0.0
Summary: A utility package for making better test assertions
Home-page: https://github.com/lunjon/asserty
Author: Jonathan Lundholm
Author-email: jon.lundholm@gmail.com
License: UNKNOWN
Platform: UNKNOWN
Classifier: Programming Language :: Python :: 3
Classifier: License :: OSI Approved :: MIT License
Classifier: Operating System :: OS Independent
